persephone/__init__.py
persephone/eigenfunctions.py
persephone/plot_gyre.py
persephone/grids/__init__.py
persephone/grids/grid_builder.py
persephone/grids/modelling.py
persephone/grids/templates/__init__.py
persephone/grids/templates/default_gyre.in
persephone/grids/templates/default_history_columns_r15140.list
persephone/grids/templates/default_history_columns_r23.05.1.list
persephone/grids/templates/default_profile_columns_r15140.list
persephone/grids/templates/default_profile_columns_r23.05.1.list
persephone/grids/templates/empty_inlist
persephone/grids/templates/kernel_example_gyre.in
persephone/kernels/__init__.py
persephone/kernels/rotation/__init__.py
persephone/kernels/rotation/kernels.py
star_persephone-0.1.2.dist-info/LICENSE
star_persephone-0.1.2.dist-info/METADATA
star_persephone-0.1.2.dist-info/WHEEL
star_persephone-0.1.2.dist-info/top_level.txt
star_persephone-0.1.2.dist-info/RECORD
