Metadata-Version: 2.1
Name: star_persephone
Version: 0.1.2
Summary: Stellar model grid management and seismic rotational kernel computations.
Author-email: "Sylvain N. Breton" <sylvain.breton@inaf.it>
License: 
Project-URL: Homepage, https://gitlab.com/sybreton/persephone
Project-URL: Documentation, https://star-persephone.readthedocs.io/en/latest/
Keywords: asteroseismology,kernels,rotation
Classifier: Programming Language :: Python :: 3
Classifier: License :: OSI Approved :: CEA CNRS Inria Logiciel Libre License, version 2.1 (CeCILL-2.1)
Classifier: Operating System :: OS Independent
Requires-Python: >=3.9
License-File: LICENSE
Requires-Dist: numpy
Requires-Dist: matplotlib
Requires-Dist: scipy
Requires-Dist: pathos
Requires-Dist: h5py
Requires-Dist: pygyre
